caltechdata_api/__init__.py
caltechdata_api/caltechdata_edit.py
caltechdata_api/caltechdata_write.py
caltechdata_api/cli.py
caltechdata_api/customize_schema.py
caltechdata_api/download_file.py
caltechdata_api/get_files.py
caltechdata_api/get_metadata.py
caltechdata_api/md_to_json.py
caltechdata_api/utils.py
caltechdata_api/vocabularies.yaml
caltechdata_api/vocabularies/date_types.yaml
caltechdata_api/vocabularies/description_types.yaml
caltechdata_api/vocabularies/identifier_types.yaml
caltechdata_api/vocabularies/licenses.csv
caltechdata_api/vocabularies/relation_types.yaml
caltechdata_api/vocabularies/resource_types.yaml
caltechdata_api/vocabularies/roles.yaml
caltechdata_api/vocabularies/title_types.yaml
caltechdata_api-1.10.6.dist-info/licenses/LICENSE
caltechdata_api-1.10.6.dist-info/METADATA
caltechdata_api-1.10.6.dist-info/WHEEL
caltechdata_api-1.10.6.dist-info/entry_points.txt
caltechdata_api-1.10.6.dist-info/top_level.txt
caltechdata_api-1.10.6.dist-info/RECORD
