Metadata-Version: 2.4
Name: caltechdata_api
Version: 1.10.6
Summary: Python wrapper for CaltechDATA API.
Home-page: https://github.com/caltechlibrary/caltechdata_api
Author: Thomas E Morrell, Rohan Bhattarai, Elizabeth Won, Alexander A Abakah, Kshemaahna Nagi
Author-email: tmorrell@caltech.edu, aabakah@caltech.edu, knagi@caltech.edu
License: MIT
Classifier: License :: OSI Approved :: MIT License
Classifier: Programming Language :: Python :: 3
Classifier: Programming Language :: Python :: 3.7
Classifier: Programming Language :: Python :: 3.8
Classifier: Programming Language :: Python :: 3.9
Classifier: Programming Language :: Python :: 3.10
Classifier: Programming Language :: Python :: Implementation :: CPython
Classifier: Operating System :: OS Independent
Requires-Python: >=3.6.0
License-File: LICENSE
Requires-Dist: requests
Requires-Dist: datacite>1.1.0
Requires-Dist: tqdm>=4.62.3
Requires-Dist: pyyaml
Requires-Dist: s3fs
Requires-Dist: cryptography
Requires-Dist: s3cmd
Dynamic: license-file
